qubership_pipelines_modules_ops/__init__.py
qubership_pipelines_modules_ops/__main__.py
qubership_pipelines_modules_ops/prepare_data.py
qubership_pipelines_modules_ops/report.py
qubership_pipelines_modules_ops/utils/__init__.py
qubership_pipelines_modules_ops/utils/utils_dictionary.py
qubership_pipelines_modules_ops/utils/utils_file.py
qubership_pipelines_modules_ops/utils/utils_github.py
qubership_pipelines_modules_ops/utils/utils_params.py
qubership_pipelines_modules_ops-0.0.4.dist-info/LICENSE
qubership_pipelines_modules_ops-0.0.4.dist-info/METADATA
qubership_pipelines_modules_ops-0.0.4.dist-info/WHEEL
qubership_pipelines_modules_ops-0.0.4.dist-info/RECORD
