Metadata-Version: 2.1
Name: qubership-pipelines-modules-ops
Version: 0.0.4
Summary: Qubership Pipelines Modules Operations library
License: Apache-2.0
Author: Qubership
Requires-Python: >=3.8,<4.0
Classifier: License :: OSI Approved :: Apache Software License
Classifier: Programming Language :: Python :: 3
Classifier: Programming Language :: Python :: 3.8
Classifier: Programming Language :: Python :: 3.9
Classifier: Programming Language :: Python :: 3.10
Classifier: Programming Language :: Python :: 3.11
Classifier: Programming Language :: Python :: 3.12
Classifier: Programming Language :: Python :: 3.13
Requires-Dist: PyYAML (>=6.0,<7.0)
Requires-Dist: click (>=8.1,<9.0)
Requires-Dist: graphlib_backport (>=1.1,<2.0) ; python_version < "3.9"
Requires-Dist: requests (==2.32.3)
